{
	"configurations" : 
	[
		{
			"directories" : 
			[
				{
					"build" : ".",
					"jsonFile" : "directory-.-Debug-d0094a50bb2071803777.json",
					"minimumCMakeVersion" : 
					{
						"string" : "3.23"
					},
					"projectIndex" : 0,
					"source" : ".",
					"targetIndexes" : 
					[
						0
					]
				}
			],
			"name" : "Debug",
			"projects" : 
			[
				{
					"directoryIndexes" : 
					[
						0
					],
					"name" : "Es1_Sett2",
					"targetIndexes" : 
					[
						0
					]
				}
			],
			"targets" : 
			[
				{
					"directoryIndex" : 0,
					"id" : "Es1_Sett2::@6890427a1f51a3e7e1df",
					"jsonFile" : "target-Es1_Sett2-Debug-0cbfbdd2053fea75167b.json",
					"name" : "Es1_Sett2",
					"projectIndex" : 0
				}
			]
		}
	],
	"kind" : "codemodel",
	"paths" : 
	{
		"build" : "C:/Users/leonardo.grimaldi2/CLionProjects/Es1-Sett2/cmake-build-debug",
		"source" : "C:/Users/leonardo.grimaldi2/CLionProjects/Es1-Sett2"
	},
	"version" : 
	{
		"major" : 2,
		"minor" : 4
	}
}
